napari_allencell_segmenter/__init__.py
napari_allencell_segmenter/_dock_widget.py
napari_allencell_segmenter/_style.py
napari_allencell_segmenter/napari.yaml
napari_allencell_segmenter/_tests/__init__.py
napari_allencell_segmenter/_tests/conftest.py
napari_allencell_segmenter/_tests/mocks.py
napari_allencell_segmenter/_tests/style_test.py
napari_allencell_segmenter/_tests/controller/__init__.py
napari_allencell_segmenter/_tests/controller/batch_processing_controller_test.py
napari_allencell_segmenter/_tests/controller/workflow_select_controller_test.py
napari_allencell_segmenter/_tests/controller/workflow_steps_controller_test.py
napari_allencell_segmenter/_tests/core/__init__.py
napari_allencell_segmenter/_tests/core/application_test.py
napari_allencell_segmenter/_tests/core/controller_test.py
napari_allencell_segmenter/_tests/core/layer_reader_test.py
napari_allencell_segmenter/_tests/core/router_test.py
napari_allencell_segmenter/_tests/core/state_test.py
napari_allencell_segmenter/_tests/core/view_manager_test.py
napari_allencell_segmenter/_tests/core/view_test.py
napari_allencell_segmenter/_tests/core/viewer_abstraction_test.py
napari_allencell_segmenter/_tests/model/__init__.py
napari_allencell_segmenter/_tests/model/segmenter_model_test.py
napari_allencell_segmenter/_tests/util/__init__.py
napari_allencell_segmenter/_tests/util/convert_test.py
napari_allencell_segmenter/_tests/util/lazy_test.py
napari_allencell_segmenter/_tests/view/__init__.py
napari_allencell_segmenter/_tests/view/_main_template_test.py
napari_allencell_segmenter/_tests/view/batch_processing_view_test.py
napari_allencell_segmenter/_tests/view/workflow_select_view_test.py
napari_allencell_segmenter/_tests/view/workflow_steps_view_test.py
napari_allencell_segmenter/_tests/widgets/__init__.py
napari_allencell_segmenter/_tests/widgets/collapsible_box_test.py
napari_allencell_segmenter/_tests/widgets/file_input_test.py
napari_allencell_segmenter/_tests/widgets/warning_message_test.py
napari_allencell_segmenter-2.1.13.dist-info/licenses/LICENSE
napari_allencell_segmenter-2.1.13.dist-info/METADATA
napari_allencell_segmenter-2.1.13.dist-info/WHEEL
napari_allencell_segmenter-2.1.13.dist-info/entry_points.txt
napari_allencell_segmenter-2.1.13.dist-info/top_level.txt
napari_allencell_segmenter-2.1.13.dist-info/RECORD
