Metadata-Version: 2.4
Name: napari-allencell-segmenter
Version: 2.1.13
Summary: A plugin that enables 3D image segmentation provided by Allen Institute for Cell Science
Author: Allen Institute for Cell Science
License: BSD-3
Project-URL: Bug Tracker, https://github.com/AllenCell/napari-allencell-segmenter/issues
Project-URL: Documentation, https://github.com/AllenCell/napari-allencell-segmenter#README.md
Project-URL: Source Code, https://github.com/AllenCell/napari-allencell-segmenter
Project-URL: User Support, https://github.com/AllenCell/napari-allencell-segmenter/issues
Classifier: Development Status :: 5 - Production/Stable
Classifier: Intended Audience :: Science/Research
Classifier: Framework :: napari
Classifier: Topic :: Scientific/Engineering
Classifier: Topic :: Scientific/Engineering :: Visualization
Classifier: Topic :: Scientific/Engineering :: Information Analysis
Classifier: Topic :: Scientific/Engineering :: Bio-Informatics
Classifier: Programming Language :: Python :: 3
Classifier: Programming Language :: Python :: 3.9
Classifier: Operating System :: OS Independent
Classifier: License :: OSI Approved :: BSD License
Requires-Python: >=3.9
License-File: LICENSE
Requires-Dist: napari<0.6.2,>=0.4.9
Requires-Dist: napari-plugin-engine>=0.1.4
Requires-Dist: numpy<2.0.0
Requires-Dist: aicssegmentation>=0.5.3
Requires-Dist: magicgui>=0.2.9
Requires-Dist: aicsimageio~=4.0.5
Requires-Dist: opencv-python-headless>=4.5.1
Requires-Dist: importlib-metadata==4.11.4
Requires-Dist: npe2
Requires-Dist: itk-core<5.4,>=5.3
Requires-Dist: itkwidgets==0.27.0
Requires-Dist: itk-meshtopolydata==0.10.0
Requires-Dist: pydantic==1.10.12
Provides-Extra: test
Requires-Dist: black>=19.10b0; extra == "test"
Requires-Dist: codecov>=2.0.22; extra == "test"
Requires-Dist: docutils<0.16,>=0.10; extra == "test"
Requires-Dist: flake8>=3.7.7; extra == "test"
Requires-Dist: psutil>=5.7.0; extra == "test"
Requires-Dist: pytest>=4.3.0; extra == "test"
Requires-Dist: pytest-cov==2.6.1; extra == "test"
Requires-Dist: pytest-raises>=0.10; extra == "test"
Requires-Dist: pytest-qt>=3.3.0; extra == "test"
Requires-Dist: quilt3>=3.1.12; extra == "test"
Provides-Extra: dev
Requires-Dist: bumpversion>=0.5.3; extra == "dev"
Requires-Dist: coverage>=5.0a4; extra == "dev"
Requires-Dist: gitchangelog>=3.0.4; extra == "dev"
Requires-Dist: ipython>=7.5.0; extra == "dev"
Requires-Dist: m2r>=0.2.1; extra == "dev"
Requires-Dist: pytest-runner>=4.4; extra == "dev"
Requires-Dist: Sphinx<3,>=2.0.0b1; extra == "dev"
Requires-Dist: sphinx_rtd_theme>=0.1.2; extra == "dev"
Requires-Dist: tox==3.25.0; extra == "dev"
Requires-Dist: twine>=1.13.0; extra == "dev"
Requires-Dist: wheel>=0.33.1; extra == "dev"
Provides-Extra: setup
Requires-Dist: pytest-runner; extra == "setup"
Dynamic: license-file
